rubric/__init__.py
rubric/autograders/__init__.py
rubric/autograders/base.py
rubric/autograders/per_criterion_grader.py
rubric/autograders/per_criterion_one_shot_grader.py
rubric/autograders/rubric_as_judge_grader.py
rubric/autograders/schemas.py
rubric/rubric.py
rubric/types.py
rubric/utils.py
rubric-2.2.0.dist-info/WHEEL
rubric-2.2.0.dist-info/METADATA
rubric-2.2.0.dist-info/RECORD
