Metadata-Version: 2.4
Name: rubric
Version: 2.2.0
Summary: rubric
Keywords: rubrics,grading,eval,rubric
Author: Gavin, Joey
Author-email: Gavin <gavin@llmdata.com>, Joey <joey@llmdata.com>
License-Expression: MIT
Classifier: Development Status :: 3 - Alpha
Classifier: Intended Audience :: Developers
Classifier: Intended Audience :: Education
Classifier: License :: OSI Approved :: MIT License
Classifier: Programming Language :: Python :: 3
Classifier: Programming Language :: Python :: 3.10
Classifier: Programming Language :: Python :: 3.11
Classifier: Programming Language :: Python :: 3.12
Classifier: Programming Language :: Python :: 3.13
Classifier: Topic :: Education
Classifier: Topic :: Software Development :: Libraries :: Python Modules
Requires-Dist: pydantic>=2.0.0
Requires-Dist: google-genai>=1.55.0
Requires-Dist: tenacity>=8.0.0
Requires-Dist: python-dotenv>=1.0.0
Requires-Dist: pyyaml>=6.0.0
Requires-Python: >=3.10
Project-URL: Homepage, https://github.com/The-LLM-Data-Company/rubric/
Project-URL: Issues, https://github.com/The-LLM-Data-Company/rubric/issues
Project-URL: Repository, https://github.com/The-LLM-Data-Company/rubric
